taskli/__init__.py
taskli/__main__.py
taskli/main.py
taskli-0.1.3.dist-info/METADATA
taskli-0.1.3.dist-info/WHEEL
taskli-0.1.3.dist-info/entry_points.txt
taskli-0.1.3.dist-info/top_level.txt
taskli-0.1.3.dist-info/RECORD
