Metadata-Version: 2.4
Name: taskli
Version: 0.1.3
Requires-Dist: typer
Requires-Dist: rich
Dynamic: requires-dist
